<?xml version="1.0" encoding="utf-8"?>
<StructureDefinition xmlns="http://hl7.org/fhir">
  <id value="dh-device-implantable-1" />
  <url value="http://ns.electronichealth.net.au/fhir/StructureDefinition/dh-device-implantable-1" />
  <version value="0.0.1" />
  <name value="DHDeviceSystem" />
  <title value="ADHA System Device" />
  <status value="draft" />
  <experimental value="false" />
  <publisher value="Australian Digital Health Agency" />
  <contact>
    <telecom>
      <system value="email" />
      <value value="help@digitalhealth.gov.au" />
    </telecom>
  </contact>
  <description value="The purpose of this profile is to define a representation of an implantable medical device for a patient for exchange usage scenarios to support the electronic exchange of health information between individuals, healthcare providers, and the My Health Record system infrastructure in Australia." />
  <copyright value="Copyright © 2022 Australian Digital Health Agency - All rights reserved. This content is licensed under a Creative Commons Attribution 4.0 International License. See https://creativecommons.org/licenses/by/4.0/." />
  <fhirVersion value="4.0.1" />
  <kind value="resource" />
  <abstract value="false" />
  <type value="Device" />
  <baseDefinition value="http://hl7.org/fhir/StructureDefinition/Device" />
  <derivation value="constraint" />
  <differential>
    <element id="Device">
      <path value="Device" />
      <constraint>
        <key value="inv-dh-dev-01"/>
        <severity value="error"/>
        <human value="The patient shall at least have a reference or an identifier with at least a system and a value"/>
        <expression value="patient.reference.exists() or patient.identifier.where(system.count() + value.count() &gt;1).exists()"/>
        <source value="http://ns.electronichealth.net.au/fhir/StructureDefinition/dh-device-implantable-1" />
      </constraint>
    </element>
    <element id="Device.udiCarrier">
      <path value="Device.udiCarrier" />
      <min value="1"/>
      <mustSupport value="true" />
    </element>
    <element id="Device.udiCarrier.deviceIdentifier">
      <path value="Device.udiCarrier.deviceIdentifier" />
      <min value="1"/>
      <mustSupport value="true" />
    </element>
    <element id="Device.udiCarrier.issuer">
      <path value="Device.udiCarrier.issuer" />
      <mustSupport value="true" />
    </element>
    <element id="Device.udiCarrier.carrierAIDC">
      <path value="Device.udiCarrier.carrierAIDC" />
      <mustSupport value="true" />
    </element>
    <element id="Device.udiCarrier.carrierHRF">
      <path value="Device.udiCarrier.carrierHRF" />
      <mustSupport value="true" />
    </element>
    <element id="Device.manufactureDate">
      <path value="Device.manufactureDate" />
      <mustSupport value="true" />
    </element>
    <element id="Device.expirationDate">
      <path value="Device.expirationDate" />
      <mustSupport value="true" />
    </element>
    <element id="Device.lotNumber">
      <path value="Device.lotNumber" />
      <mustSupport value="true" />
    </element>
    <element id="Device.serialNumber">
      <path value="Device.serialNumber" />
      <mustSupport value="true" />
    </element>
    <element id="Device.type">
      <path value="Device.type" />
      <mustSupport value="true" />
    </element>
    <element id="Device.patient">
      <path value="Device.patient" />
      <min value="1"/>
      <type>
        <code value="Reference" />
        <targetProfile value="http://ns.electronichealth.net.au/fhir/StructureDefinition/dh-patient-core-1" />
      </type>
      <mustSupport value="true" />
    </element>
  </differential>
</StructureDefinition>
